gltflib/__init__.py
gltflib/__version__.py
gltflib/gltf.py
gltflib/gltf_resource.py
gltflib/py.typed
gltflib/enums/__init__.py
gltflib/enums/accessor_type.py
gltflib/enums/alpha_mode.py
gltflib/enums/animation_target_path.py
gltflib/enums/buffer_target.py
gltflib/enums/camera_type.py
gltflib/enums/component_type.py
gltflib/enums/interpolation.py
gltflib/enums/primitive_mode.py
gltflib/models/__init__.py
gltflib/models/accessor.py
gltflib/models/animation.py
gltflib/models/animation_sampler.py
gltflib/models/asset.py
gltflib/models/attributes.py
gltflib/models/base_model.py
gltflib/models/buffer.py
gltflib/models/buffer_view.py
gltflib/models/camera.py
gltflib/models/channel.py
gltflib/models/gltf_model.py
gltflib/models/image.py
gltflib/models/material.py
gltflib/models/mesh.py
gltflib/models/named_base_model.py
gltflib/models/node.py
gltflib/models/normal_texture_info.py
gltflib/models/occlusion_texture_info.py
gltflib/models/orthographic_camera_info.py
gltflib/models/pbr_metallic_roughness.py
gltflib/models/perspective_camera_info.py
gltflib/models/primitive.py
gltflib/models/sampler.py
gltflib/models/scene.py
gltflib/models/skin.py
gltflib/models/sparse.py
gltflib/models/sparse_indices.py
gltflib/models/sparse_values.py
gltflib/models/target.py
gltflib/models/texture.py
gltflib/models/texture_info.py
gltflib/utils/__init__.py
gltflib/utils/data_utils.py
gltflib/utils/file_utils.py
gltflib/utils/json_utils.py
tests/e2e/__init__.py
tests/e2e/test_roundtrip.py
tests/unit/__init__.py
tests/unit/test_gltf.py
tests/unit/test_gltf_model.py
gltflib-1.0.13.dist-info/LICENSE
gltflib-1.0.13.dist-info/METADATA
gltflib-1.0.13.dist-info/WHEEL
gltflib-1.0.13.dist-info/top_level.txt
gltflib-1.0.13.dist-info/RECORD
