Metadata-Version: 2.1
Name: gltflib
Version: 1.0.13
Summary: Library for parsing, creating, and converting glTF 2.0 files in Python.
Home-page: http://github.com/sergkr/gltflib
Author: Sergey Krilov
License: MIT
Classifier: License :: OSI Approved :: MIT License
Classifier: Programming Language :: Python
Classifier: Programming Language :: Python :: 3
Classifier: Programming Language :: Python :: 3.6
Classifier: Programming Language :: Python :: Implementation :: CPython
Classifier: Programming Language :: Python :: Implementation :: PyPy
Requires-Python: >=3.6.0
License-File: LICENSE
